bnvd/__init__.py
bnvd/client.py
bnvd/exceptions.py
bnvd-1.0.1.dist-info/licenses/license
bnvd-1.0.1.dist-info/METADATA
bnvd-1.0.1.dist-info/WHEEL
bnvd-1.0.1.dist-info/top_level.txt
bnvd-1.0.1.dist-info/RECORD
