Metadata-Version: 2.4
Name: bnvd
Version: 1.0.1
Summary: Cliente Python para a API do Banco Nacional de Vulnerabilidades Digitais bnvd.org
Home-page: https://github.com/azurejoga/bnvd
Author: Juan Mathews Rebello Santos
Author-email: contato@bnvd.org
Classifier: Programming Language :: Python :: 3
Classifier: License :: OSI Approved :: MIT License
Classifier: Operating System :: OS Independent
Requires-Python: >=3.7
License-File: license
Requires-Dist: requests
Dynamic: author
Dynamic: author-email
Dynamic: classifier
Dynamic: description
Dynamic: description-content-type
Dynamic: home-page
Dynamic: license-file
Dynamic: requires-dist
Dynamic: requires-python
Dynamic: summary
